geegle/__init__.py
geegle/cache_service.py
geegle/chat_service.py
geegle/cli.py
geegle/config.py
geegle/main.py
geegle/secure_config.py
geegle/session_manager.py
geegle-0.0.3.dist-info/METADATA
geegle-0.0.3.dist-info/WHEEL
geegle-0.0.3.dist-info/entry_points.txt
geegle-0.0.3.dist-info/top_level.txt
geegle-0.0.3.dist-info/RECORD
