Metadata-Version: 2.4
Name: geegle
Version: 0.0.3
Summary: A CLI chat app with web search and session management
Author-email: oha <aaronoh2015@gmail.com>
License: Apache 2.0
Keywords: chat,cli,search,openai
Classifier: Development Status :: 4 - Beta
Classifier: Intended Audience :: Developers
Classifier: License :: OSI Approved :: Apache Software License
Classifier: Programming Language :: Python :: 3
Classifier: Programming Language :: Python :: 3.7
Classifier: Programming Language :: Python :: 3.8
Classifier: Programming Language :: Python :: 3.9
Classifier: Programming Language :: Python :: 3.10
Requires-Python: >=3.7
Requires-Dist: openai==1.73.0
Requires-Dist: anthropic==0.49.0
Requires-Dist: pydantic==2.11.3
Requires-Dist: python-dotenv==1.1.0
Requires-Dist: rich==13.0.0
Requires-Dist: prompt_toolkit==3.0.0
Requires-Dist: requests==2.32.3
Requires-Dist: selenium==4.31.0
Requires-Dist: webdriver-manager==4.0.0
Requires-Dist: beautifulsoup4==4.13.3
Requires-Dist: keyring==25.6.0
